x52.py
x52_control-1.0.0.dist-info/LICENSE.txt
x52_control-1.0.0.dist-info/METADATA
x52_control-1.0.0.dist-info/WHEEL
x52_control-1.0.0.dist-info/top_level.txt
x52_control-1.0.0.dist-info/RECORD
