Metadata-Version: 2.1
Name: x52-control
Version: 1.0.0
Summary: Configures LEDs and display on Logitech X52 HOTAS
Home-page: https://gitlab.com/Nerdeiro/x52-control
Author: Bento Loewenstein Silveira
Author-email: anarch157a@ninjazumbi.com
License: GPL2
Platform: UNKNOWN
Classifier: License :: OSI Approved :: GNU General Public License v2 or later (GPLv2+)
Classifier: Programming Language :: Python :: 3
Classifier: Programming Language :: Python :: 3.6
Classifier: Programming Language :: Python :: 3.7
Classifier: Programming Language :: Python :: 3.8
Classifier: Programming Language :: Python :: 3.9
Classifier: Intended Audience :: End Users/Desktop
Classifier: Intended Audience :: Developers
Classifier: Topic :: System :: Hardware :: Hardware Drivers
Classifier: Operating System :: POSIX :: Linux
